otpylib/__init__.py
otpylib/atom/__init__.py
otpylib/atom/core.py
otpylib/atom/data.py
otpylib/atom/table.py
otpylib/distribution/__init__.py
otpylib/distribution/api.py
otpylib/distribution/connection.py
otpylib/distribution/constants.py
otpylib/distribution/epmd.py
otpylib/distribution/etf.py
otpylib/distribution/node.py
otpylib/distribution/protocol.py
otpylib/dynamic_supervisor/__init__.py
otpylib/dynamic_supervisor/atoms.py
otpylib/dynamic_supervisor/core.py
otpylib/gen_server/__init__.py
otpylib/gen_server/atoms.py
otpylib/gen_server/core.py
otpylib/gen_server/data.py
otpylib/gen_statem/__init__.py
otpylib/gen_statem/atoms.py
otpylib/gen_statem/core.py
otpylib/helpers/__init__.py
otpylib/helpers/core.py
otpylib/inet/__init__.py
otpylib/inet/atoms.py
otpylib/inet/data.py
otpylib/inet/tcp.py
otpylib/inet/udp.py
otpylib/module/__init__.py
otpylib/module/atoms.py
otpylib/module/core.py
otpylib/module/data.py
otpylib/node/__init__.py
otpylib/node/core.py
otpylib/process/__init__.py
otpylib/process/api.py
otpylib/runtime/__init__.py
otpylib/runtime/atom_utils.py
otpylib/runtime/atoms.py
otpylib/runtime/core.py
otpylib/runtime/data.py
otpylib/runtime/registry.py
otpylib/runtime/backends/__init__.py
otpylib/runtime/backends/base.py
otpylib/runtime/backends/asyncio_backend/__init__.py
otpylib/runtime/backends/asyncio_backend/backend.py
otpylib/runtime/backends/asyncio_backend/connection.py
otpylib/runtime/backends/asyncio_backend/distribution.py
otpylib/runtime/backends/asyncio_backend/epmd.py
otpylib/runtime/backends/asyncio_backend/node.py
otpylib/runtime/backends/asyncio_backend/pid.py
otpylib/runtime/backends/asyncio_backend/process.py
otpylib/runtime/backends/asyncio_backend/tcp.py
otpylib/runtime/backends/asyncio_backend/timing_wheel.py
otpylib/spam/__init__.py
otpylib/spam/backend.py
otpylib/spam/core.py
otpylib/spam/data.py
otpylib/spam/runtime.py
otpylib/spam/scheduler.py
otpylib/supervisor/__init__.py
otpylib/supervisor/atoms.py
otpylib/supervisor/core.py
otpylib-0.5.12.dist-info/licenses/LICENSE.txt
otpylib-0.5.12.dist-info/METADATA
otpylib-0.5.12.dist-info/WHEEL
otpylib-0.5.12.dist-info/top_level.txt
otpylib-0.5.12.dist-info/RECORD
