Metadata-Version: 2.4
Name: otpylib
Version: 0.5.12
Summary: The OTP framework for Python.
Author-email: HeroesLament <nunya@biz.net>
License: MIT
Project-URL: homepage, https://github.com/HeroesLament/otpylib
Project-URL: repository, https://github.com/HeroesLament/otpylib
Project-URL: documentation, https://github.com/HeroesLament/otpylib#readme
Project-URL: issues, https://github.com/HeroesLament/otpylib/issues
Keywords: anyio,trio,asyncio,async,otp,actors,supervision
Classifier: Development Status :: 3 - Alpha
Classifier: Framework :: AsyncIO
Classifier: Intended Audience :: Developers
Classifier: Topic :: Software Development :: Libraries :: Python Modules
Classifier: Topic :: System :: Distributed Computing
Classifier: Programming Language :: Python :: 3
Classifier: Programming Language :: Python :: 3.10
Classifier: Programming Language :: Python :: 3.11
Classifier: Programming Language :: Python :: 3.12
Classifier: License :: OSI Approved :: MIT License
Requires-Python: >=3.10
License-File: LICENSE.txt
Requires-Dist: loguru>=0.7.3
Requires-Dist: result>=0.17.0
Requires-Dist: tenacity>=8.0.0
Provides-Extra: dev
Requires-Dist: pytest>=8.4.2; extra == "dev"
Requires-Dist: pytest-asyncio>=1.2.0; extra == "dev"
Requires-Dist: pytest-cov>=7.0.0; extra == "dev"
Dynamic: license-file
